simphile/__init__.py
simphile/compression_similarity.py
simphile/euclidian_similarity.py
simphile/fisher.py
simphile/jaccard_similarity.py
simphile/language_classification_example.py
simphile/naive_bayes.py
simphile/sets.py
simphile/text_processor.py
simphile/text_utils.py
simphile-1.0.4.dist-info/licenses/LICENSE
simphile-1.0.4.dist-info/METADATA
simphile-1.0.4.dist-info/WHEEL
simphile-1.0.4.dist-info/top_level.txt
simphile-1.0.4.dist-info/RECORD
